{"py/object": "rasa.core.featurizers.tracker_featurizers.MaxHistoryTrackerFeaturizer", "state_featurizer": {"py/object": "rasa.core.featurizers.single_state_featurizer.SingleStateFeaturizer", "_default_feature_states": {"intent": {"FirstName": 0, "LastName": 1, "affirm": 2, "agree": 3, "back": 4, "bot_challenge": 5, "bye": 6, "deny": 7, "disagree": 8, "feedback": 9, "goodbye": 10, "greet": 11, "inform": 12, "mood_great": 13, "mood_unhappy": 14, "navigate_to": 15, "nlu_fallback": 16, "out_of_scope": 17, "play_song": 18, "request_details": 19, "restart": 20, "session_start": 21, "thanks": 22, "weather": 23}, "action_name": {"action_listen": 0, "action_restart": 1, "action_session_start": 2, "action_default_fallback": 3, "action_deactivate_loop": 4, "action_revert_fallback_events": 5, "action_default_ask_affirmation": 6, "action_default_ask_rephrase": 7, "action_two_stage_fallback": 8, "action_unlikely_intent": 9, "action_back": 10, "...": 11, "action_extract_slots": 12, "action_weather_api": 13, "action_play_song": 14, "utter_greet": 15, "utter_goodbye": 16, "utter_thanks": 17, "action_last_name": 18, "action_feedback": 19, "action_submit": 20, "utter_ask_firstN": 21, "utter_ask_lastN": 22, "utter_ask_feedback": 23, "utter_ask_for_feedback": 24, "utter_cheer_up": 25, "utter_did_that_help": 26, "utter_happy": 27, "utter_iamabot": 28, "utter_navigate": 29, "utter_submit": 30, "form_info": 31}, "entities": {"address": 0, "city": 1, "number": 2, "query": 3, "song": 4}, "slots": {"feedback_0": 0, "firstN_0": 1, "lastN_0": 2}, "active_loop": {"form_info": 0}}, "action_texts": [], "entity_tag_specs": null}, "max_history": 5, "remove_duplicates": true}